[
    {
        "name": "Xiaomi 3D Men Electric Shaver Razor Enchen BlackStone3 IPX7 Waterproof",
        "num_review": "1",
        "price": null,
        "original_price": null,
        "url": "https://www.cigabuy.com/xiaomi-3d-men-electric-shaver-razor-enchen-blackstone3-ipx7-waterproof-p-20146.html"
    },
    {
        "name": "100 LED Solar Light  Solar Lamp Powered Sunlight 3 Modes PIR Motion Sensor",
        "num_review": "1",
        "price": null,
        "original_price": null,
        "url": "https://www.cigabuy.com/100-led-solar-light-solar-lamp-powered-sunlight-3-modes-pir-motion-sensor-p-19318.html"
    },
    {
        "name": "Food Grade Silicone Cupcake Baking Mold Mould Non Stick Muffin Cup Baking Cup",
        "num_review": "0",
        "price": "$0.12",
        "original_price": "$0.12 ",
        "url": "https://www.cigabuy.com/food-grade-silicone-cupcake-baking-mold-mould-non-stick-muffin-cup-baking-cup-p-17054.html"
    },
    {
        "name": "X96Q Android 10 TV Box Quad Core Allwinner H313 4K 2GB RAM 16GB ROM",
        "num_review": "3",
        "price": "$22.23",
        "original_price": "$37.53 ",
        "url": "https://www.cigabuy.com/x96q-android-10-tv-box-quad-core-allwinner-h313-4k-2gb-ram-16gb-rom-p-18997.html"
    },
    {
        "name": "Enchen BlackStone Portable Men's 3D Electric Shaver Type-c Rechargeable",
        "num_review": "0",
        "price": "$8.19",
        "original_price": "$17.68 ",
        "url": "https://www.cigabuy.com/enchen-blackstone-portable-mens-3d-electric-shaver-type-rechargeable-p-21990.html"
    },
    {
        "name": "COOLBOSS Sports Digital Watch Wristwatch With Rubber Band For Kids",
        "num_review": "7",
        "price": "$1.18",
        "original_price": "$2.15 ",
        "url": "https://www.cigabuy.com/coolboss-sports-digital-watch-wristwatch-with-rubber-band-for-kids-p-14293.html"
    },
    {
        "name": "12V 150W Mini Portable Car Air Purification Heater Demisting Defroster 2 Gears",
        "num_review": "0",
        "price": null,
        "original_price": null,
        "url": "https://www.cigabuy.com/12v-150w-mini-portable-car-air-purification-heater-demisting-defroster-2-gears-p-20450.html"
    },
    {
        "name": "20pcs Strong BBQ Kit BBQ Tools Camp Shovel Cooking Roast Fork Stainless Steel",
        "num_review": "0",
        "price": "$8.84",
        "original_price": "$8.85 ",
        "url": "https://www.cigabuy.com/20pcs-strong-bbq-kit-bbq-tools-camp-shovel-cooking-roast-fork-stainless-steel-p-20154.html"
    },
    {
        "name": "Baellerry Men Wallet Luxury Long Clutch Handy Bag Male PU Leather Purse",
        "num_review": "0",
        "price": "$5.54",
        "original_price": "$5.55 ",
        "url": "https://www.cigabuy.com/baellerry-men-wallet-luxury-long-clutch-handy-bag-male-pu-leather-purse-p-20149.html"
    },
    {
        "name": "Y5 Color Screen Wristband Watch Smart Electronics Bracelet",
        "num_review": "0",
        "price": "$3.54",
        "original_price": "$8.81 ",
        "url": "https://www.cigabuy.com/y5-color-screen-wristband-watch-smart-electronics-bracelet-p-21131.html"
    },
    {
        "name": "Night Light Multi-Color Star Projector Plush",
        "num_review": "0",
        "price": "$0.59",
        "original_price": "$3.19 ",
        "url": "https://www.cigabuy.com/night-light-multi-color-star-projector-plush-p-20715.html"
    },
    {
        "name": "Multipurpose Level Laser Measure Line 8ft w Adjusted Standard and Metric Rulers",
        "num_review": "1",
        "price": "$2.24",
        "original_price": "$4.53 ",
        "url": "https://www.cigabuy.com/multipurpose-level-laser-measure-line-8ft-w-adjusted-standard-and-metric-rulers-p-14827.html"
    },
    {
        "name": "IP67 P8 Smart Watch Wristband Men Women Monitor Smartwatch Tracker For Phone",
        "num_review": "0",
        "price": "$11.70",
        "original_price": "$15.32 ",
        "url": "https://www.cigabuy.com/ip67-p8-smart-watch-wristband-men-women-monitor-smartwatch-tracker-for-phone-p-18585.html"
    },
    {
        "name": "Projector Light 4.9ft Green & Blue Aluminum Laser Show",
        "num_review": "2",
        "price": "$2.34",
        "original_price": "$39.92 ",
        "url": "https://www.cigabuy.com/projector-light-49ft-green-blue-aluminum-laser-show-p-11522.html"
    },
    {
        "name": "1/2 pcs Mini Airtight Sealer Machine for Plastic Bag - Assorted Color",
        "num_review": "0",
        "price": null,
        "original_price": null,
        "url": "https://www.cigabuy.com/12-pcs-mini-airtight-sealer-machine-for-plastic-bag-assorted-color-p-21194.html"
    },
    {
        "name": "S450 3.5mm Foldable Wireless Stereo Bluetooth Headphone w/ TF FM",
        "num_review": "0",
        "price": "$2.36",
        "original_price": "$7.78 ",
        "url": "https://www.cigabuy.com/s450-35mm-foldable-wireless-stereo-bluetooth-headphone-w-tf-fm-p-19818.html"
    },
    {
        "name": "AXGIO Super Mini Nano Wireless Stereo Earphone with Mic for Cellphone",
        "num_review": "0",
        "price": "$1.18",
        "original_price": "$19.25 ",
        "url": "https://www.cigabuy.com/axgio-super-mini-nano-wireless-stereo-earphone-with-mic-for-cellphone-p-20703.html"
    },
    {
        "name": "Swan Base Holder Dinnerware Set with 5 Forks and 5 Spoons - Gold",
        "num_review": "0",
        "price": "$5.85",
        "original_price": "$24.02 ",
        "url": "https://www.cigabuy.com/swan-base-holder-dinnerware-set-with-5-forks-and-5-spoons-gold-p-21308.html"
    },
    {
        "name": "JM-PJ1010 10 in 1 Multifunctional Pliers Outdoor Folding Plier With Knife",
        "num_review": "4",
        "price": "$5.78",
        "original_price": "$17.99 ",
        "url": "https://www.cigabuy.com/jm-pj1010-10-in-1-multifunctional-pliers-outdoor-folding-plier-with-knife-p-14549.html"
    },
    {
        "name": "Mini I8X Wireless Bluetooth V4.2 In-Ear Headphone for iPhone 6 - Right Earbuds",
        "num_review": "0",
        "price": "$1.18",
        "original_price": "$3.53 ",
        "url": "https://www.cigabuy.com/mini-i8x-wireless-bluetooth-v42-in-ear-headphone-for-iphone-6-right-earbuds-p-21404.html"
    },
    {
        "name": "5-in-1 Multi-Functional Mini Handheld Car Air Pump",
        "num_review": "1",
        "price": "$4.36",
        "original_price": "$29.53 ",
        "url": "https://www.cigabuy.com/5-in-1-multi-functional-mini-handheld-car-air-pump-p-14854.html"
    },
    {
        "name": "JY011 2.4G Drone with WIFI FPV HD Camera Real time RC Quadcopter",
        "num_review": "0",
        "price": "$11.70",
        "original_price": "$107.30 ",
        "url": "https://www.cigabuy.com/jy011-24g-drone-with-wifi-fpv-hd-camera-real-time-rc-quadcopter-p-21725.html"
    },
    {
        "name": "Mini Bluetooth Earbud 6 Hour Playtime Car Headset with Mic for iPhone",
        "num_review": "0",
        "price": "$1.18",
        "original_price": "$16.53 ",
        "url": "https://www.cigabuy.com/mini-bluetooth-earbud-6-hour-playtime-car-headset-with-mic-for-iphone-p-19725.html"
    },
    {
        "name": "Shini Q940 3.5mm Sport Headset Ear Hook For Cell Phone",
        "num_review": "0",
        "price": "$1.18",
        "original_price": "$5.19 ",
        "url": "https://www.cigabuy.com/shini-q940-35mm-sport-headset-ear-hook-for-cell-phone-p-21662.html"
    }
]